qlip_serve/client/README-PyPI.md
qlip_serve/client/__init__.py
qlip_serve/client/client.py
qlip_serve/client/pyproject.toml
qlip_serve_client-0.1.17.dist-info/METADATA
qlip_serve_client-0.1.17.dist-info/WHEEL
qlip_serve_client-0.1.17.dist-info/RECORD
